ztfeatureslib/__init__.py
ztfeatureslib/__main__.py
ztfeatureslib/main.py
ztfeatureslib/schema/pii_prompt.py
ztfeatureslib/tools/__init__.py
ztfeatureslib/tools/api_key_hashing.py
ztfeatureslib/tools/pii_detection/__init__.py
ztfeatureslib/tools/pii_detection/detect_pii.py
ztfeatureslib/tools/pii_detection/schema/__init__.py
ztfeatureslib/tools/pii_detection/schema/detect_anonymize_pii.py
ztfeatureslib/tools/pii_detection/schema/pii_prompt.py
ztfeatureslib/tools/pii_detection/services/__init__.py
ztfeatureslib/tools/pii_detection/services/detect_anonymize_pii_service.py
ztfeatureslib/tools/pii_detection/services/detect_pii_gliner.py
ztfeatureslib/tools/pii_detection/utils/__init__.py
ztfeatureslib/tools/pii_detection/utils/constants.py
zt_features_lib-0.1.6.dist-info/entry_points.txt
zt_features_lib-0.1.6.dist-info/METADATA
zt_features_lib-0.1.6.dist-info/WHEEL
zt_features_lib-0.1.6.dist-info/RECORD
