Metadata-Version: 2.3
Name: zt-features-lib
Version: 0.1.6
Summary: A Python library with FastAPI endpoints, ready for PyPI.
License: MIT
Author: Your Name
Author-email: your.email@example.com
Requires-Python: >=3.12,<3.13
Classifier: License :: OSI Approved :: MIT License
Classifier: Programming Language :: Python :: 3
Classifier: Programming Language :: Python :: 3.12
Requires-Dist: aiofiles (==24.1.0)
Requires-Dist: faker (>=25.0.0,<26.0.0)
Requires-Dist: fastapi (>=0.110.0,<0.111.0)
Requires-Dist: gliner (>=0.2.0,<0.3.0)
Requires-Dist: loguru (>=0.7.2,<0.8.0)
Requires-Dist: pandas (>=2.2.2,<3.0.0)
Requires-Dist: presidio-analyzer (>=2.2.270,<3.0.0)
Requires-Dist: uvicorn (>=0.29.0,<0.30.0)
